{
  "round": 0,
  "system": "tea",
  "system_type": "tea",
  "pedestal": {"name": "teastore", "tag": "1.4.0"},
  "benchmark": {"name": "clickhouse", "tag": "1.0.0"},
  "defaults": {"interval": 10, "pre_duration": 5},
  "_strategy": "After hot DB patch (chart 0.1.2 + jmeter busybox override): probe with PodFailure on webui (new short app name in 0.1.2 chart, was teastore-webui in 0.1.1).",
  "candidates": [
    {"id": "te04", "app": "webui",       "chaos_type": "PodFailure", "params": {}, "duration_override": 6},
    {"id": "te05", "app": "persistence", "chaos_type": "PodFailure", "params": {}, "duration_override": 6},
    {"id": "te06", "app": "auth",        "chaos_type": "PodFailure", "params": {}, "duration_override": 6}
  ]
}
